morphata/__init__.py
morphata/acceptance.py
morphata/automaton.py
morphata/examples/__init__.py
morphata/examples/ltl.py
morphata/examples/nfa.py
morphata/examples/strel.py
morphata/hoa/__init__.py
morphata/hoa/__main__.py
morphata/hoa/acc_expr.py
morphata/hoa/exporter.py
morphata/hoa/hoa.lark
morphata/hoa/parser.py
morphata/py.typed
morphata/spec.py
morphata/utils.py
morphata-1.0.0.dist-info/WHEEL
morphata-1.0.0.dist-info/METADATA
morphata-1.0.0.dist-info/RECORD
