Metadata-Version: 2.3
Name: morphata
Version: 1.0.0
Summary: Flexible automata representations for regular and ω-regular languages.
Author: Anand Balakrishnan
Requires-Dist: typing-extensions
Requires-Dist: lark
Requires-Dist: logic-asts>=1.4.1
Requires-Dist: networkx
Requires-Dist: types-networkx
Requires-Dist: attrs>=25.4.0
Requires-Python: >=3.12
